WordleBot/Guesser.py
WordleBot/__init__.py
WordleBot/wordle_dictionary.py
wordlesolver-0.2.1.dist-info/LICENSE
wordlesolver-0.2.1.dist-info/METADATA
wordlesolver-0.2.1.dist-info/WHEEL
wordlesolver-0.2.1.dist-info/entry_points.txt
wordlesolver-0.2.1.dist-info/top_level.txt
wordlesolver-0.2.1.dist-info/RECORD
