Metadata-Version: 2.1
Name: wordlesolver
Version: 0.2.1
Summary: This bot solves wordles.
Home-page: https://github.com/gdold/WordleBot
Author: Gavin Dold
License: The MIT License (MIT)
Platform: UNKNOWN
Requires-Python: >=3.6
License-File: LICENSE
Requires-Dist: argparse
Requires-Dist: numpy
Requires-Dist: pandas
